geoexplorer/__init__.py
geoexplorer/models.py
geoexplorer/tests.py
geoexplorer/static/geoexplorer/externals/GeoExt/resources/css/geoext-all.css
geoexplorer/static/geoexplorer/externals/GeoExt/resources/css/gxtheme-gray.css
geoexplorer/static/geoexplorer/externals/GeoExt/resources/css/layerlegend.css
geoexplorer/static/geoexplorer/externals/GeoExt/resources/css/popup.css
geoexplorer/static/geoexplorer/externals/GeoExt/resources/css/symbolizercolumn.css
geoexplorer/static/geoexplorer/externals/GeoExt/resources/images/default/anchor-top.png
geoexplorer/static/geoexplorer/externals/GeoExt/resources/images/default/anchor.png
geoexplorer/static/geoexplorer/externals/GeoExt/resources/images/default/bullet_arrow_down.png
geoexplorer/static/geoexplorer/externals/GeoExt/resources/images/default/bullet_arrow_up.png
geoexplorer/static/geoexplorer/externals/GeoExt/resources/images/default/delete.png
geoexplorer/static/geoexplorer/externals/GeoExt/resources/images/gray/anchor-top.png
geoexplorer/static/geoexplorer/externals/GeoExt/resources/images/gray/anchor.png
geoexplorer/static/geoexplorer/externals/PrintPreview/resources/css/printpreview.css
geoexplorer/static/geoexplorer/externals/PrintPreview/resources/images/north_arrow.png
geoexplorer/static/geoexplorer/externals/PrintPreview/resources/images/silk/printer.png
geoexplorer/static/geoexplorer/externals/ext/ext-all-debug-w-comments.js
geoexplorer/static/geoexplorer/externals/ext/ext-all-debug.js
geoexplorer/static/geoexplorer/externals/ext/ext-all.js
geoexplorer/static/geoexplorer/externals/ext/adapter/ext/ext-base-debug.js
geoexplorer/static/geoexplorer/externals/ext/adapter/ext/ext-base.js
geoexplorer/static/geoexplorer/externals/ext/adapter/jquery/ext-jquery-adapter-debug.js
geoexplorer/static/geoexplorer/externals/ext/adapter/jquery/ext-jquery-adapter.js
geoexplorer/static/geoexplorer/externals/ext/adapter/prototype/ext-prototype-adapter-debug.js
django_geoexplorer-4.0.43.dist-info/LICENSE
django_geoexplorer-4.0.43.dist-info/METADATA
django_geoexplorer-4.0.43.dist-info/WHEEL
django_geoexplorer-4.0.43.dist-info/top_level.txt
django_geoexplorer-4.0.43.dist-info/RECORD
