Metadata-Version: 2.1
Name: django-geoexplorer
Version: 4.0.43
Summary: Use GeoExplorer in your django projects
Home-page: https://github.com/GeoNode/django-geoexplorer
Author: Alessio Fabiani
Author-email: alessio.fabiani@gmail.com
License: LGPL, see LICENSE file.
Download-URL: http://pypi.python.org/pypi/django-geoexplorer/
Platform: UNKNOWN
Classifier: Topic :: Utilities
Classifier: Natural Language :: English
Classifier: Operating System :: OS Independent
Classifier: Intended Audience :: Developers
Classifier: Environment :: Web Environment
Classifier: Framework :: Django
Classifier: Development Status :: 5 - Production/Stable
Classifier: Programming Language :: Python :: 2.7
